<?xml version='1.0' standalone='yes' ?>
<LVData xmlns="http://www.ni.com/LVData">
<Version>16.0</Version>
<LvVariant>
<Name>Value</Name>
<Cluster>
<Name>ILC Serial Settings</Name>
<NumElts>9</NumElts>
<U32>
<Name>Baud Rate</Name>
<Val>921600</Val>
</U32>
<U16>
<Name>Data Bits</Name>
<Val>8</Val>
</U16>
<EW>
<Name>Parity</Name>
<Choice>None</Choice>
<Choice>Odd</Choice>
<Choice>Even</Choice>
<Choice>Mark</Choice>
<Choice>Space</Choice>
<Val>0</Val>
</EW>
<U16>
<Name>Flow Control</Name>
<Val>0</Val>
</U16>
<U16>
<Name>Stop Bits</Name>
<Val>10</Val>
</U16>
<U32>
<Name>Timeout (ms)</Name>
<Val>20</Val>
</U32>
<U32>
<Name>Byte Count</Name>
<Val>256</Val>
</U32>
<Boolean>
<Name>Enable Termination Character</Name>
<Val>0</Val>
</Boolean>
<U8>
<Name>Termination Char</Name>
<Val>200</Val>
</U8>
</Cluster>
</LvVariant>
</LVData>